README.md
setup.cfg
setup.py
ccr/CodeCompileRun.py
ccr/__init__.py
ccr/cli.py
ccr/client.py
ccr/utility.py
ccr.egg-info/PKG-INFO
ccr.egg-info/SOURCES.txt
ccr.egg-info/dependency_links.txt
ccr.egg-info/entry_points.txt
ccr.egg-info/requires.txt
ccr.egg-info/top_level.txt
ccr/pickle/codechefs_languages_map.pickle
ccr/pickle/geeksforgeeks_languages_map.pickle
ccr/pickle/supported_languages.pickle
ccr/pickle/supported_languages_extension.pickle
test/test.py